krokimagic/__init__.py
krokimagic/krokimagic.py
jupyter_kroki_magic-0.1.0.dist-info/LICENSE
jupyter_kroki_magic-0.1.0.dist-info/METADATA
jupyter_kroki_magic-0.1.0.dist-info/WHEEL
jupyter_kroki_magic-0.1.0.dist-info/top_level.txt
jupyter_kroki_magic-0.1.0.dist-info/RECORD
