Metadata-Version: 2.1
Name: jupyter-kroki-magic
Version: 0.1.0
Summary: A Jupyter Notebook %%magic for drawing diagram using kroki.io
Home-page: https://github.com/sunhwan/jupyter-kroki-magic
Author: Sunhwan Jo
Author-email: sunhwanj@gmail.com
License: MIT
Keywords: ipython,jupyter
Platform: UNKNOWN
Classifier: Intended Audience :: Developers
Classifier: Intended Audience :: Science/Research
Classifier: Programming Language :: Python
Classifier: Programming Language :: Python :: 3.5
Requires-Dist: jupyter
Requires-Dist: ipywidgets
